LICENSE
MANIFEST.in
README.md
README.rst
setup.py
surpyvor/__init__.py
surpyvor/fixref.py
surpyvor/haplomerge.py
surpyvor/parse_arguments.py
surpyvor/plots.py
surpyvor/purge2d.py
surpyvor/surpyvor.py
surpyvor/utils.py
surpyvor/version.py
surpyvor.egg-info/PKG-INFO
surpyvor.egg-info/SOURCES.txt
surpyvor.egg-info/dependency_links.txt
surpyvor.egg-info/entry_points.txt
surpyvor.egg-info/requires.txt
surpyvor.egg-info/top_level.txt